{"id":790,"name":"cosmoem","image":"https://raw.githubusercontent.com/PokeAPI/sprites/master/sprites/pokemon/other/official-artwork/790.png","shinyImage":"https://raw.githubusercontent.com/PokeAPI/sprites/master/sprites/pokemon/other/official-artwork/shiny/790.png","types":["psychic"],"stats":[{"name":"hp","value":43},{"name":"attack","value":29},{"name":"defense","value":131},{"name":"special-attack","value":29},{"name":"special-defense","value":131},{"name":"speed","value":37}],"statTotal":400,"introducedGeneration":7,"abilities":[{"name":"sturdy","hidden":false,"introducedIn":3,"description":"Prevents being KOed from full HP, leaving 1 HP instead. Protects against the one-hit KO moves regardless of HP.","effectChanges":[{"versionGroup":"black-white","description":"Does not prevent regular KOs from full HP."}]}],"moves":[{"name":"teleport","details":[{"level":1,"method":"level-up","versionGroup":"sun-moon"},{"level":1,"method":"level-up","versionGroup":"ultra-sun-ultra-moon"},{"level":1,"method":"level-up","versionGroup":"sword-shield"},{"level":1,"method":"level-up","versionGroup":"scarlet-violet"}],"type":"psychic","category":"status","power":null,"accuracy":null,"pp":20,"pastValues":[{"versionGroup":"lets-go-pikachu-lets-go-eevee","type":null,"power":null,"accuracy":null,"pp":null}]},{"name":"cosmic-power","details":[{"level":0,"method":"level-up","versionGroup":"sun-moon"},{"level":1,"method":"level-up","versionGroup":"sun-moon"},{"level":0,"method":"level-up","versionGroup":"ultra-sun-ultra-moon"},{"level":1,"method":"level-up","versionGroup":"ultra-sun-ultra-moon"},{"level":0,"method":"level-up","versionGroup":"sword-shield"},{"level":1,"method":"level-up","versionGroup":"sword-shield"},{"level":0,"method":"machine","versionGroup":"sword-shield"},{"level":0,"method":"level-up","versionGroup":"scarlet-violet"}],"type":"psychic","category":"status","power":null,"accuracy":null,"pp":20,"pastValues":[]}],"evolutionRoot":{"name":"cosmog","generation":7,"condition":null,"varieties":["cosmog"],"children":[{"name":"cosmoem","generation":7,"condition":"Lvl 43","varieties":["cosmoem"],"children":[{"name":"solgaleo","generation":7,"condition":"Lvl 53","varieties":["solgaleo"],"children":[]},{"name":"lunala","generation":7,"condition":"Lvl 53","varieties":["lunala"],"children":[]}]}]},"alternativeForms":[]}