{"id":701,"name":"hawlucha","image":"https://raw.githubusercontent.com/PokeAPI/sprites/master/sprites/pokemon/other/official-artwork/701.png","shinyImage":"https://raw.githubusercontent.com/PokeAPI/sprites/master/sprites/pokemon/other/official-artwork/shiny/701.png","types":["fighting","flying"],"stats":[{"name":"hp","value":78},{"name":"attack","value":92},{"name":"defense","value":75},{"name":"special-attack","value":74},{"name":"special-defense","value":63},{"name":"speed","value":118}],"statTotal":500,"introducedGeneration":6,"abilities":[{"name":"limber","hidden":false,"introducedIn":3,"description":"Prevents paralysis.","effectChanges":[]},{"name":"unburden","hidden":false,"introducedIn":4,"description":"Doubles Speed upon using or losing a held item.","effectChanges":[]},{"name":"mold-breaker","hidden":true,"introducedIn":4,"description":"Bypasses targets' abilities if they could hinder or prevent a move.","effectChanges":[]}],"moves":[{"name":"karate-chop","details":[{"level":4,"method":"level-up","versionGroup":"x-y"},{"level":4,"method":"level-up","versionGroup":"omega-ruby-alpha-sapphire"},{"level":4,"method":"level-up","versionGroup":"sun-moon"},{"level":4,"method":"level-up","versionGroup":"ultra-sun-ultra-moon"}],"type":"fighting","category":"physical","power":50,"accuracy":100,"pp":25,"pastValues":[{"versionGroup":"gold-silver","type":"normal","power":null,"accuracy":null,"pp":null}]},{"name":"mega-punch","details":[{"level":0,"method":"machine","versionGroup":"sword-shield"}],"type":"normal","category":"physical","power":80,"accuracy":85,"pp":20,"pastValues":[]},{"name":"fire-punch","details":[{"level":0,"method":"tutor","versionGroup":"omega-ruby-alpha-sapphire"},{"level":0,"method":"tutor","versionGroup":"ultra-sun-ultra-moon"},{"level":0,"method":"machine","versionGroup":"sword-shield"},{"level":0,"method":"machine","versionGroup":"scarlet-violet"}],"type":"fire","category":"physical","power":75,"accuracy":100,"pp":15,"pastValues":[]},{"name":"thunder-punch","details":[{"level":0,"method":"tutor","versionGroup":"omega-ruby-alpha-sapphire"},{"level":0,"method":"tutor","versionGroup":"ultra-sun-ultra-moon"},{"level":0,"method":"machine","versionGroup":"sword-shield"},{"level":0,"method":"machine","versionGroup":"scarlet-violet"}],"type":"electric","category":"physical","power":75,"accuracy":100,"pp":15,"pastValues":[]},{"name":"swords-dance","details":[{"level":60,"method":"level-up","versionGroup":"x-y"},{"level":0,"method":"machine","versionGroup":"x-y"},{"level":60,"method":"level-up","versionGroup":"omega-ruby-alpha-sapphire"},{"level":0,"method":"machine","versionGroup":"omega-ruby-alpha-sapphire"},{"level":60,"method":"level-up","versionGroup":"sun-moon"},{"level":0,"method":"machine","versionGroup":"sun-moon"},{"level":60,"method":"level-up","versionGroup":"ultra-sun-ultra-moon"},{"level":0,"method":"machine","versionGroup":"ultra-sun-ultra-moon"},{"level":40,"method":"level-up","versionGroup":"sword-shield"},{"level":0,"method":"machine","versionGroup":"sword-shield"},{"level":40,"method":"level-up","versionGroup":"scarlet-violet"},{"level":0,"method":"machine","versionGroup":"scarlet-violet"}],"type":"normal","category":"status","power":null,"accuracy":null,"pp":20,"pastValues":[{"versionGroup":"x-y","type":null,"power":null,"accuracy":null,"pp":30}]},{"name":"cut","details":[{"level":0,"method":"machine","versionGroup":"x-y"},{"level":0,"method":"machine","versionGroup":"omega-ruby-alpha-sapphire"}],"type":"normal","category":"physical","power":50,"accuracy":95,"pp":30,"pastValues":[]},{"name":"wing-attack","details":[{"level":8,"method":"level-up","versionGroup":"x-y"},{"level":8,"method":"level-up","versionGroup":"omega-ruby-alpha-sapphire"},{"level":8,"method":"level-up","versionGroup":"sun-moon"},{"level":8,"method":"level-up","versionGroup":"ultra-sun-ultra-moon"},{"level":4,"method":"level-up","versionGroup":"sword-shield"},{"level":4,"method":"level-up","versionGroup":"scarlet-violet"}],"type":"flying","category":"physical","power":60,"accuracy":100,"pp":35,"pastValues":[{"versionGroup":"gold-silver","type":null,"power":35,"accuracy":null,"pp":null}]},{"name":"fly","details":[{"level":0,"method":"machine","versionGroup":"x-y"},{"level":0,"method":"machine","versionGroup":"omega-ruby-alpha-sapphire"},{"level":0,"method":"machine","versionGroup":"sun-moon"},{"level":0,"method":"machine","versionGroup":"ultra-sun-ultra-moon"},{"level":0,"method":"machine","versionGroup":"sword-shield"},{"level":0,"method":"machine","versionGroup":"scarlet-violet"}],"type":"flying","category":"physical","power":90,"accuracy":95,"pp":15,"pastValues":[{"versionGroup":"diamond-pearl","type":null,"power":70,"accuracy":null,"pp":null}]},{"name":"mega-kick","details":[{"level":0,"method":"machine","versionGroup":"sword-shield"}],"type":"normal","category":"physical","power":120,"accuracy":75,"pp":5,"pastValues":[]},{"name":"tackle","details":[{"level":1,"method":"level-up","versionGroup":"x-y"},{"level":1,"method":"level-up","versionGroup":"omega-ruby-alpha-sapphire"},{"level":1,"method":"level-up","versionGroup":"sun-moon"},{"level":1,"method":"level-up","versionGroup":"ultra-sun-ultra-moon"},{"level":1,"method":"level-up","versionGroup":"sword-shield"},{"level":1,"method":"level-up","versionGroup":"scarlet-violet"}],"type":"normal","category":"physical","power":40,"accuracy":100,"pp":35,"pastValues":[{"versionGroup":"black-white","type":null,"power":35,"accuracy":95,"pp":null},{"versionGroup":"sun-moon","type":null,"power":50,"accuracy":null,"pp":null}]},{"name":"body-slam","details":[{"level":0,"method":"machine","versionGroup":"scarlet-violet"}],"type":"normal","category":"physical","power":85,"accuracy":100,"pp":15,"pastValues":[]},{"name":"take-down","details":[{"level":0,"method":"machine","versionGroup":"scarlet-violet"}],"type":"normal","category":"physical","power":90,"accuracy":85,"pp":20,"pastValues":[]},{"name":"hyper-beam","details":[{"level":0,"method":"machine","versionGroup":"scarlet-violet"}],"type":"normal","category":"special","power":150,"accuracy":90,"pp":5,"pastValues":[]},{"name":"submission","details":[{"level":24,"method":"level-up","versionGroup":"sword-shield"}],"type":"fighting","category":"physical","power":80,"accuracy":80,"pp":20,"pastValues":[{"versionGroup":"x-y","type":null,"power":null,"accuracy":null,"pp":25}]},{"name":"low-kick","details":[{"level":0,"method":"tutor","versionGroup":"omega-ruby-alpha-sapphire"},{"level":0,"method":"tutor","versionGroup":"ultra-sun-ultra-moon"},{"level":0,"method":"machine","versionGroup":"sword-shield"},{"level":0,"method":"machine","versionGroup":"scarlet-violet"}],"type":"fighting","category":"physical","power":null,"accuracy":100,"pp":20,"pastValues":[{"versionGroup":"ruby-sapphire","type":null,"power":50,"accuracy":90,"pp":null}]},{"name":"strength","details":[{"level":0,"method":"machine","versionGroup":"x-y"},{"level":0,"method":"machine","versionGroup":"omega-ruby-alpha-sapphire"}],"type":"normal","category":"physical","power":80,"accuracy":100,"pp":15,"pastValues":[]},{"name":"dig","details":[{"level":0,"method":"machine","versionGroup":"x-y"},{"level":0,"method":"machine","versionGroup":"omega-ruby-alpha-sapphire"},{"level":0,"method":"machine","versionGroup":"sword-shield"},{"level":0,"method":"machine","versionGroup":"scarlet-violet"}],"type":"ground","category":"physical","power":80,"accuracy":100,"pp":10,"pastValues":[{"versionGroup":"gold-silver","type":null,"power":100,"accuracy":null,"pp":null},{"versionGroup":"diamond-pearl","type":null,"power":60,"accuracy":null,"pp":null}]},{"name":"toxic","details":[{"level":0,"method":"machine","versionGroup":"x-y"},{"level":0,"method":"machine","versionGroup":"omega-ruby-alpha-sapphire"},{"level":0,"method":"machine","versionGroup":"sun-moon"},{"level":0,"method":"machine","versionGroup":"ultra-sun-ultra-moon"}],"type":"poison","category":"status","power":null,"accuracy":90,"pp":10,"pastValues":[{"versionGroup":"black-white","type":null,"power":null,"accuracy":85,"pp":null}]},{"name":"agility","details":[{"level":0,"method":"egg","versionGroup":"x-y"},{"level":0,"method":"egg","versionGroup":"omega-ruby-alpha-sapphire"},{"level":0,"method":"egg","versionGroup":"sun-moon"},{"level":0,"method":"egg","versionGroup":"ultra-sun-ultra-moon"},{"level":0,"method":"machine","versionGroup":"sword-shield"},{"level":0,"method":"machine","versionGroup":"scarlet-violet"}],"type":"psychic","category":"status","power":null,"accuracy":null,"pp":30,"pastValues":[]},{"name":"double-team","details":[{"level":0,"method":"machine","versionGroup":"x-y"},{"level":0,"method":"machine","versionGroup":"omega-ruby-alpha-sapphire"},{"level":0,"method":"machine","versionGroup":"sun-moon"},{"level":0,"method":"machine","versionGroup":"ultra-sun-ultra-moon"}],"type":"normal","category":"status","power":null,"accuracy":null,"pp":15,"pastValues":[]},{"name":"swift","details":[{"level":0,"method":"machine","versionGroup":"sword-shield"},{"level":0,"method":"machine","versionGroup":"scarlet-violet"}],"type":"normal","category":"special","power":60,"accuracy":null,"pp":20,"pastValues":[]},{"name":"high-jump-kick","details":[{"level":44,"method":"level-up","versionGroup":"x-y"},{"level":44,"method":"level-up","versionGroup":"omega-ruby-alpha-sapphire"},{"level":44,"method":"level-up","versionGroup":"sun-moon"},{"level":44,"method":"level-up","versionGroup":"ultra-sun-ultra-moon"},{"level":48,"method":"level-up","versionGroup":"sword-shield"},{"level":48,"method":"level-up","versionGroup":"scarlet-violet"}],"type":"fighting","category":"physical","power":130,"accuracy":90,"pp":10,"pastValues":[{"versionGroup":"diamond-pearl","type":null,"power":85,"accuracy":null,"pp":null},{"versionGroup":"black-white","type":null,"power":100,"accuracy":null,"pp":20}]},{"name":"sky-attack","details":[{"level":48,"method":"level-up","versionGroup":"x-y"},{"level":48,"method":"level-up","versionGroup":"omega-ruby-alpha-sapphire"},{"level":0,"method":"tutor","versionGroup":"omega-ruby-alpha-sapphire"},{"level":48,"method":"level-up","versionGroup":"sun-moon"},{"level":48,"method":"level-up","versionGroup":"ultra-sun-ultra-moon"},{"level":0,"method":"tutor","versionGroup":"ultra-sun-ultra-moon"},{"level":56,"method":"level-up","versionGroup":"sword-shield"},{"level":56,"method":"level-up","versionGroup":"scarlet-violet"}],"type":"flying","category":"physical","power":140,"accuracy":90,"pp":5,"pastValues":[{"versionGroup":"gold-silver","type":null,"power":null,"accuracy":null,"pp":null},{"versionGroup":"lets-go-pikachu-lets-go-eevee","type":null,"power":140,"accuracy":null,"pp":null},{"versionGroup":"sword-shield","type":null,"power":200,"accuracy":null,"pp":null}]},{"name":"rest","details":[{"level":0,"method":"machine","versionGroup":"x-y"},{"level":0,"method":"machine","versionGroup":"omega-ruby-alpha-sapphire"},{"level":0,"method":"machine","versionGroup":"sun-moon"},{"level":0,"method":"machine","versionGroup":"ultra-sun-ultra-moon"},{"level":0,"method":"machine","versionGroup":"sword-shield"},{"level":0,"method":"machine","versionGroup":"scarlet-violet"}],"type":"psychic","category":"status","power":null,"accuracy":null,"pp":5,"pastValues":[]},{"name":"rock-slide","details":[{"level":0,"method":"machine","versionGroup":"x-y"},{"level":0,"method":"machine","versionGroup":"omega-ruby-alpha-sapphire"},{"level":0,"method":"machine","versionGroup":"sun-moon"},{"level":0,"method":"machine","versionGroup":"ultra-sun-ultra-moon"},{"level":0,"method":"machine","versionGroup":"sword-shield"},{"level":0,"method":"machine","versionGroup":"scarlet-violet"}],"type":"rock","category":"physical","power":75,"accuracy":90,"pp":10,"pastValues":[{"versionGroup":"gold-silver","type":null,"power":null,"accuracy":null,"pp":null}]},{"name":"substitute","details":[{"level":0,"method":"machine","versionGroup":"x-y"},{"level":0,"method":"machine","versionGroup":"omega-ruby-alpha-sapphire"},{"level":0,"method":"machine","versionGroup":"sun-moon"},{"level":0,"method":"machine","versionGroup":"ultra-sun-ultra-moon"},{"level":0,"method":"machine","versionGroup":"sword-shield"},{"level":0,"method":"machine","versionGroup":"scarlet-violet"}],"type":"normal","category":"status","power":null,"accuracy":null,"pp":10,"pastValues":[]},{"name":"thief","details":[{"level":0,"method":"machine","versionGroup":"scarlet-violet"}],"type":"dark","category":"physical","power":60,"accuracy":100,"pp":25,"pastValues":[{"versionGroup":"x-y","type":null,"power":40,"accuracy":null,"pp":10}]},{"name":"snore","details":[{"level":0,"method":"tutor","versionGroup":"omega-ruby-alpha-sapphire"},{"level":0,"method":"tutor","versionGroup":"ultra-sun-ultra-moon"},{"level":0,"method":"machine","versionGroup":"sword-shield"}],"type":"normal","category":"special","power":50,"accuracy":100,"pp":15,"pastValues":[{"versionGroup":"x-y","type":null,"power":40,"accuracy":null,"pp":null}]},{"name":"reversal","details":[{"level":0,"method":"machine","versionGroup":"sword-shield"},{"level":0,"method":"machine","versionGroup":"scarlet-violet"}],"type":"fighting","category":"physical","power":null,"accuracy":100,"pp":15,"pastValues":[]},{"name":"protect","details":[{"level":0,"method":"machine","versionGroup":"x-y"},{"level":0,"method":"machine","versionGroup":"omega-ruby-alpha-sapphire"},{"level":0,"method":"machine","versionGroup":"sun-moon"},{"level":0,"method":"machine","versionGroup":"ultra-sun-ultra-moon"},{"level":0,"method":"machine","versionGroup":"sword-shield"},{"level":0,"method":"machine","versionGroup":"scarlet-violet"}],"type":"normal","category":"status","power":null,"accuracy":null,"pp":10,"pastValues":[]},{"name":"detect","details":[{"level":1,"method":"level-up","versionGroup":"x-y"},{"level":1,"method":"level-up","versionGroup":"omega-ruby-alpha-sapphire"},{"level":1,"method":"level-up","versionGroup":"sun-moon"},{"level":1,"method":"level-up","versionGroup":"ultra-sun-ultra-moon"},{"level":8,"method":"level-up","versionGroup":"sword-shield"},{"level":8,"method":"level-up","versionGroup":"scarlet-violet"}],"type":"fighting","category":"status","power":null,"accuracy":null,"pp":5,"pastValues":[]},{"name":"endure","details":[{"level":0,"method":"machine","versionGroup":"sword-shield"},{"level":0,"method":"machine","versionGroup":"scarlet-violet"}],"type":"normal","category":"status","power":null,"accuracy":null,"pp":10,"pastValues":[]},{"name":"false-swipe","details":[{"level":0,"method":"machine","versionGroup":"x-y"},{"level":0,"method":"machine","versionGroup":"omega-ruby-alpha-sapphire"},{"level":0,"method":"machine","versionGroup":"sun-moon"},{"level":0,"method":"machine","versionGroup":"ultra-sun-ultra-moon"},{"level":0,"method":"machine","versionGroup":"sword-shield"},{"level":0,"method":"machine","versionGroup":"scarlet-violet"}],"type":"normal","category":"physical","power":40,"accuracy":100,"pp":40,"pastValues":[]},{"name":"swagger","details":[{"level":0,"method":"machine","versionGroup":"x-y"},{"level":0,"method":"machine","versionGroup":"omega-ruby-alpha-sapphire"},{"level":0,"method":"machine","versionGroup":"sun-moon"},{"level":0,"method":"machine","versionGroup":"ultra-sun-ultra-moon"}],"type":"normal","category":"status","power":null,"accuracy":85,"pp":15,"pastValues":[{"versionGroup":"sun-moon","type":null,"power":null,"accuracy":90,"pp":null}]},{"name":"steel-wing","details":[{"level":0,"method":"machine","versionGroup":"x-y"},{"level":0,"method":"machine","versionGroup":"omega-ruby-alpha-sapphire"},{"level":0,"method":"machine","versionGroup":"sun-moon"},{"level":0,"method":"machine","versionGroup":"ultra-sun-ultra-moon"},{"level":0,"method":"machine","versionGroup":"sword-shield"}],"type":"steel","category":"physical","power":70,"accuracy":90,"pp":25,"pastValues":[]},{"name":"mean-look","details":[{"level":0,"method":"egg","versionGroup":"sword-shield"},{"level":0,"method":"egg","versionGroup":"scarlet-violet"}],"type":"normal","category":"status","power":null,"accuracy":null,"pp":5,"pastValues":[]},{"name":"attract","details":[{"level":0,"method":"machine","versionGroup":"x-y"},{"level":0,"method":"machine","versionGroup":"omega-ruby-alpha-sapphire"},{"level":0,"method":"machine","versionGroup":"sun-moon"},{"level":0,"method":"machine","versionGroup":"ultra-sun-ultra-moon"},{"level":0,"method":"machine","versionGroup":"sword-shield"}],"type":"normal","category":"status","power":null,"accuracy":100,"pp":15,"pastValues":[]},{"name":"sleep-talk","details":[{"level":0,"method":"machine","versionGroup":"x-y"},{"level":0,"method":"machine","versionGroup":"omega-ruby-alpha-sapphire"},{"level":0,"method":"machine","versionGroup":"sun-moon"},{"level":0,"method":"machine","versionGroup":"ultra-sun-ultra-moon"},{"level":0,"method":"machine","versionGroup":"sword-shield"},{"level":0,"method":"machine","versionGroup":"scarlet-violet"}],"type":"normal","category":"status","power":null,"accuracy":null,"pp":10,"pastValues":[]},{"name":"return","details":[{"level":0,"method":"machine","versionGroup":"x-y"},{"level":0,"method":"machine","versionGroup":"omega-ruby-alpha-sapphire"},{"level":0,"method":"machine","versionGroup":"sun-moon"},{"level":0,"method":"machine","versionGroup":"ultra-sun-ultra-moon"}],"type":"normal","category":"physical","power":null,"accuracy":100,"pp":20,"pastValues":[]},{"name":"frustration","details":[{"level":0,"method":"machine","versionGroup":"x-y"},{"level":0,"method":"machine","versionGroup":"omega-ruby-alpha-sapphire"},{"level":0,"method":"machine","versionGroup":"sun-moon"},{"level":0,"method":"machine","versionGroup":"ultra-sun-ultra-moon"}],"type":"normal","category":"physical","power":null,"accuracy":100,"pp":20,"pastValues":[]},{"name":"baton-pass","details":[{"level":0,"method":"egg","versionGroup":"x-y"},{"level":0,"method":"egg","versionGroup":"omega-ruby-alpha-sapphire"},{"level":0,"method":"egg","versionGroup":"sun-moon"},{"level":0,"method":"egg","versionGroup":"ultra-sun-ultra-moon"},{"level":0,"method":"machine","versionGroup":"sword-shield"},{"level":0,"method":"machine","versionGroup":"scarlet-violet"}],"type":"normal","category":"status","power":null,"accuracy":null,"pp":40,"pastValues":[]},{"name":"encore","details":[{"level":20,"method":"level-up","versionGroup":"x-y"},{"level":20,"method":"level-up","versionGroup":"omega-ruby-alpha-sapphire"},{"level":20,"method":"level-up","versionGroup":"sun-moon"},{"level":20,"method":"level-up","versionGroup":"ultra-sun-ultra-moon"},{"level":16,"method":"level-up","versionGroup":"sword-shield"},{"level":0,"method":"machine","versionGroup":"sword-shield"},{"level":16,"method":"level-up","versionGroup":"scarlet-violet"},{"level":0,"method":"machine","versionGroup":"scarlet-violet"}],"type":"normal","category":"status","power":null,"accuracy":100,"pp":5,"pastValues":[]},{"name":"hidden-power","details":[{"level":0,"method":"machine","versionGroup":"x-y"},{"level":0,"method":"machine","versionGroup":"omega-ruby-alpha-sapphire"},{"level":0,"method":"machine","versionGroup":"sun-moon"},{"level":0,"method":"machine","versionGroup":"ultra-sun-ultra-moon"}],"type":"normal","category":"special","power":60,"accuracy":100,"pp":15,"pastValues":[{"versionGroup":"x-y","type":null,"power":1,"accuracy":null,"pp":null}]},{"name":"cross-chop","details":[{"level":0,"method":"egg","versionGroup":"sword-shield"},{"level":0,"method":"egg","versionGroup":"scarlet-violet"}],"type":"fighting","category":"physical","power":100,"accuracy":80,"pp":5,"pastValues":[]},{"name":"rain-dance","details":[{"level":0,"method":"machine","versionGroup":"x-y"},{"level":0,"method":"machine","versionGroup":"omega-ruby-alpha-sapphire"},{"level":0,"method":"machine","versionGroup":"sun-moon"},{"level":0,"method":"machine","versionGroup":"ultra-sun-ultra-moon"},{"level":0,"method":"machine","versionGroup":"sword-shield"},{"level":0,"method":"machine","versionGroup":"scarlet-violet"}],"type":"water","category":"status","power":null,"accuracy":null,"pp":5,"pastValues":[]},{"name":"sunny-day","details":[{"level":0,"method":"machine","versionGroup":"x-y"},{"level":0,"method":"machine","versionGroup":"omega-ruby-alpha-sapphire"},{"level":0,"method":"machine","versionGroup":"sun-moon"},{"level":0,"method":"machine","versionGroup":"ultra-sun-ultra-moon"},{"level":0,"method":"machine","versionGroup":"sword-shield"},{"level":0,"method":"machine","versionGroup":"scarlet-violet"}],"type":"fire","category":"status","power":null,"accuracy":null,"pp":5,"pastValues":[]},{"name":"rock-smash","details":[{"level":0,"method":"machine","versionGroup":"x-y"},{"level":0,"method":"machine","versionGroup":"omega-ruby-alpha-sapphire"}],"type":"fighting","category":"physical","power":40,"accuracy":100,"pp":15,"pastValues":[{"versionGroup":"diamond-pearl","type":null,"power":20,"accuracy":null,"pp":null}]},{"name":"uproar","details":[{"level":0,"method":"machine","versionGroup":"scarlet-violet"}],"type":"normal","category":"special","power":90,"accuracy":100,"pp":10,"pastValues":[{"versionGroup":"black-white","type":null,"power":50,"accuracy":null,"pp":null}]},{"name":"torment","details":[{"level":0,"method":"machine","versionGroup":"x-y"},{"level":0,"method":"machine","versionGroup":"omega-ruby-alpha-sapphire"},{"level":0,"method":"machine","versionGroup":"sun-moon"},{"level":0,"method":"machine","versionGroup":"ultra-sun-ultra-moon"}],"type":"dark","category":"status","power":null,"accuracy":100,"pp":15,"pastValues":[]},{"name":"facade","details":[{"level":0,"method":"machine","versionGroup":"x-y"},{"level":0,"method":"machine","versionGroup":"omega-ruby-alpha-sapphire"},{"level":0,"method":"machine","versionGroup":"sun-moon"},{"level":0,"method":"machine","versionGroup":"ultra-sun-ultra-moon"},{"level":0,"method":"machine","versionGroup":"sword-shield"},{"level":0,"method":"machine","versionGroup":"scarlet-violet"}],"type":"normal","category":"physical","power":70,"accuracy":100,"pp":20,"pastValues":[]},{"name":"focus-punch","details":[{"level":0,"method":"tutor","versionGroup":"omega-ruby-alpha-sapphire"},{"level":0,"method":"tutor","versionGroup":"ultra-sun-ultra-moon"},{"level":0,"method":"machine","versionGroup":"scarlet-violet"}],"type":"fighting","category":"physical","power":150,"accuracy":100,"pp":20,"pastValues":[]},{"name":"taunt","details":[{"level":0,"method":"machine","versionGroup":"x-y"},{"level":0,"method":"machine","versionGroup":"omega-ruby-alpha-sapphire"},{"level":0,"method":"machine","versionGroup":"sun-moon"},{"level":0,"method":"machine","versionGroup":"ultra-sun-ultra-moon"},{"level":32,"method":"level-up","versionGroup":"sword-shield"},{"level":0,"method":"machine","versionGroup":"sword-shield"},{"level":32,"method":"level-up","versionGroup":"scarlet-violet"},{"level":0,"method":"machine","versionGroup":"scarlet-violet"}],"type":"dark","category":"status","power":null,"accuracy":100,"pp":20,"pastValues":[]},{"name":"helping-hand","details":[{"level":0,"method":"tutor","versionGroup":"omega-ruby-alpha-sapphire"},{"level":0,"method":"tutor","versionGroup":"ultra-sun-ultra-moon"},{"level":0,"method":"machine","versionGroup":"sword-shield"},{"level":0,"method":"machine","versionGroup":"scarlet-violet"}],"type":"normal","category":"status","power":null,"accuracy":null,"pp":20,"pastValues":[]},{"name":"superpower","details":[{"level":0,"method":"tutor","versionGroup":"omega-ruby-alpha-sapphire"},{"level":0,"method":"tutor","versionGroup":"ultra-sun-ultra-moon"},{"level":0,"method":"machine","versionGroup":"sword-shield"}],"type":"fighting","category":"physical","power":120,"accuracy":100,"pp":5,"pastValues":[]},{"name":"revenge","details":[{"level":0,"method":"machine","versionGroup":"sword-shield"}],"type":"fighting","category":"physical","power":60,"accuracy":100,"pp":10,"pastValues":[]},{"name":"brick-break","details":[{"level":0,"method":"machine","versionGroup":"x-y"},{"level":0,"method":"machine","versionGroup":"omega-ruby-alpha-sapphire"},{"level":0,"method":"machine","versionGroup":"sun-moon"},{"level":0,"method":"machine","versionGroup":"ultra-sun-ultra-moon"},{"level":0,"method":"machine","versionGroup":"sword-shield"},{"level":24,"method":"level-up","versionGroup":"scarlet-violet"},{"level":0,"method":"machine","versionGroup":"scarlet-violet"}],"type":"fighting","category":"physical","power":75,"accuracy":100,"pp":15,"pastValues":[]},{"name":"endeavor","details":[{"level":36,"method":"level-up","versionGroup":"x-y"},{"level":36,"method":"level-up","versionGroup":"omega-ruby-alpha-sapphire"},{"level":0,"method":"tutor","versionGroup":"omega-ruby-alpha-sapphire"},{"level":36,"method":"level-up","versionGroup":"sun-moon"},{"level":36,"method":"level-up","versionGroup":"ultra-sun-ultra-moon"},{"level":0,"method":"tutor","versionGroup":"ultra-sun-ultra-moon"},{"level":52,"method":"level-up","versionGroup":"sword-shield"},{"level":52,"method":"level-up","versionGroup":"scarlet-violet"},{"level":0,"method":"machine","versionGroup":"scarlet-violet"}],"type":"normal","category":"physical","power":null,"accuracy":100,"pp":5,"pastValues":[]},{"name":"secret-power","details":[{"level":0,"method":"machine","versionGroup":"omega-ruby-alpha-sapphire"}],"type":"normal","category":"physical","power":70,"accuracy":100,"pp":20,"pastValues":[]},{"name":"feather-dance","details":[{"level":40,"method":"level-up","versionGroup":"x-y"},{"level":40,"method":"level-up","versionGroup":"omega-ruby-alpha-sapphire"},{"level":40,"method":"level-up","versionGroup":"sun-moon"},{"level":40,"method":"level-up","versionGroup":"ultra-sun-ultra-moon"},{"level":20,"method":"level-up","versionGroup":"sword-shield"},{"level":20,"method":"level-up","versionGroup":"scarlet-violet"},{"level":0,"method":"machine","versionGroup":"scarlet-violet"}],"type":"flying","category":"status","power":null,"accuracy":100,"pp":15,"pastValues":[]},{"name":"mud-sport","details":[{"level":0,"method":"egg","versionGroup":"x-y"},{"level":0,"method":"egg","versionGroup":"omega-ruby-alpha-sapphire"},{"level":0,"method":"egg","versionGroup":"sun-moon"},{"level":0,"method":"egg","versionGroup":"ultra-sun-ultra-moon"}],"type":"ground","category":"status","power":null,"accuracy":null,"pp":15,"pastValues":[]},{"name":"rock-tomb","details":[{"level":0,"method":"machine","versionGroup":"x-y"},{"level":0,"method":"machine","versionGroup":"omega-ruby-alpha-sapphire"},{"level":0,"method":"machine","versionGroup":"sun-moon"},{"level":0,"method":"machine","versionGroup":"ultra-sun-ultra-moon"},{"level":0,"method":"machine","versionGroup":"sword-shield"},{"level":0,"method":"machine","versionGroup":"scarlet-violet"}],"type":"rock","category":"physical","power":60,"accuracy":95,"pp":15,"pastValues":[{"versionGroup":"x-y","type":null,"power":50,"accuracy":80,"pp":10}]},{"name":"aerial-ace","details":[{"level":16,"method":"level-up","versionGroup":"x-y"},{"level":0,"method":"machine","versionGroup":"x-y"},{"level":16,"method":"level-up","versionGroup":"omega-ruby-alpha-sapphire"},{"level":0,"method":"machine","versionGroup":"omega-ruby-alpha-sapphire"},{"level":16,"method":"level-up","versionGroup":"sun-moon"},{"level":0,"method":"machine","versionGroup":"sun-moon"},{"level":16,"method":"level-up","versionGroup":"ultra-sun-ultra-moon"},{"level":0,"method":"machine","versionGroup":"ultra-sun-ultra-moon"},{"level":12,"method":"level-up","versionGroup":"sword-shield"},{"level":12,"method":"level-up","versionGroup":"scarlet-violet"},{"level":0,"method":"machine","versionGroup":"scarlet-violet"}],"type":"flying","category":"physical","power":60,"accuracy":null,"pp":20,"pastValues":[]},{"name":"bulk-up","details":[{"level":0,"method":"machine","versionGroup":"x-y"},{"level":0,"method":"machine","versionGroup":"omega-ruby-alpha-sapphire"},{"level":0,"method":"machine","versionGroup":"sun-moon"},{"level":0,"method":"machine","versionGroup":"ultra-sun-ultra-moon"},{"level":0,"method":"machine","versionGroup":"sword-shield"},{"level":0,"method":"machine","versionGroup":"scarlet-violet"}],"type":"fighting","category":"status","power":null,"accuracy":null,"pp":20,"pastValues":[]},{"name":"bounce","details":[{"level":32,"method":"level-up","versionGroup":"x-y"},{"level":32,"method":"level-up","versionGroup":"omega-ruby-alpha-sapphire"},{"level":0,"method":"tutor","versionGroup":"omega-ruby-alpha-sapphire"},{"level":32,"method":"level-up","versionGroup":"sun-moon"},{"level":32,"method":"level-up","versionGroup":"ultra-sun-ultra-moon"},{"level":0,"method":"tutor","versionGroup":"ultra-sun-ultra-moon"},{"level":28,"method":"level-up","versionGroup":"sword-shield"},{"level":0,"method":"machine","versionGroup":"sword-shield"},{"level":28,"method":"level-up","versionGroup":"scarlet-violet"}],"type":"flying","category":"physical","power":85,"accuracy":85,"pp":5,"pastValues":[]},{"name":"roost","details":[{"level":12,"method":"level-up","versionGroup":"x-y"},{"level":0,"method":"machine","versionGroup":"x-y"},{"level":12,"method":"level-up","versionGroup":"omega-ruby-alpha-sapphire"},{"level":0,"method":"machine","versionGroup":"omega-ruby-alpha-sapphire"},{"level":12,"method":"level-up","versionGroup":"sun-moon"},{"level":0,"method":"machine","versionGroup":"sun-moon"},{"level":12,"method":"level-up","versionGroup":"ultra-sun-ultra-moon"},{"level":0,"method":"machine","versionGroup":"ultra-sun-ultra-moon"},{"level":36,"method":"level-up","versionGroup":"sword-shield"},{"level":36,"method":"level-up","versionGroup":"scarlet-violet"}],"type":"flying","category":"status","power":null,"accuracy":null,"pp":5,"pastValues":[]},{"name":"feint","details":[{"level":0,"method":"egg","versionGroup":"ultra-sun-ultra-moon"},{"level":0,"method":"egg","versionGroup":"sword-shield"},{"level":0,"method":"egg","versionGroup":"scarlet-violet"}],"type":"normal","category":"physical","power":30,"accuracy":100,"pp":10,"pastValues":[{"versionGroup":"black-white","type":null,"power":50,"accuracy":null,"pp":null}]},{"name":"tailwind","details":[{"level":0,"method":"tutor","versionGroup":"omega-ruby-alpha-sapphire"},{"level":0,"method":"tutor","versionGroup":"ultra-sun-ultra-moon"}],"type":"flying","category":"status","power":null,"accuracy":null,"pp":15,"pastValues":[{"versionGroup":"x-y","type":null,"power":null,"accuracy":null,"pp":30}]},{"name":"u-turn","details":[{"level":0,"method":"machine","versionGroup":"x-y"},{"level":0,"method":"machine","versionGroup":"omega-ruby-alpha-sapphire"},{"level":0,"method":"machine","versionGroup":"sun-moon"},{"level":0,"method":"machine","versionGroup":"ultra-sun-ultra-moon"},{"level":0,"method":"machine","versionGroup":"sword-shield"},{"level":0,"method":"machine","versionGroup":"scarlet-violet"}],"type":"bug","category":"physical","power":70,"accuracy":100,"pp":20,"pastValues":[]},{"name":"close-combat","details":[{"level":0,"method":"machine","versionGroup":"sword-shield"},{"level":0,"method":"machine","versionGroup":"scarlet-violet"}],"type":"fighting","category":"physical","power":120,"accuracy":100,"pp":5,"pastValues":[]},{"name":"payback","details":[{"level":0,"method":"machine","versionGroup":"x-y"},{"level":0,"method":"machine","versionGroup":"omega-ruby-alpha-sapphire"},{"level":0,"method":"machine","versionGroup":"sun-moon"},{"level":0,"method":"machine","versionGroup":"ultra-sun-ultra-moon"},{"level":0,"method":"machine","versionGroup":"sword-shield"}],"type":"dark","category":"physical","power":50,"accuracy":100,"pp":10,"pastValues":[]},{"name":"assurance","details":[{"level":0,"method":"machine","versionGroup":"sword-shield"}],"type":"dark","category":"physical","power":60,"accuracy":100,"pp":10,"pastValues":[{"versionGroup":"x-y","type":null,"power":50,"accuracy":null,"pp":null}]},{"name":"fling","details":[{"level":24,"method":"level-up","versionGroup":"x-y"},{"level":0,"method":"machine","versionGroup":"x-y"},{"level":24,"method":"level-up","versionGroup":"omega-ruby-alpha-sapphire"},{"level":0,"method":"machine","versionGroup":"omega-ruby-alpha-sapphire"},{"level":24,"method":"level-up","versionGroup":"sun-moon"},{"level":0,"method":"machine","versionGroup":"sun-moon"},{"level":24,"method":"level-up","versionGroup":"ultra-sun-ultra-moon"},{"level":0,"method":"machine","versionGroup":"ultra-sun-ultra-moon"},{"level":0,"method":"machine","versionGroup":"sword-shield"},{"level":0,"method":"machine","versionGroup":"scarlet-violet"}],"type":"dark","category":"physical","power":null,"accuracy":100,"pp":10,"pastValues":[]},{"name":"me-first","details":[{"level":0,"method":"egg","versionGroup":"x-y"},{"level":0,"method":"egg","versionGroup":"omega-ruby-alpha-sapphire"},{"level":0,"method":"egg","versionGroup":"sun-moon"},{"level":0,"method":"egg","versionGroup":"ultra-sun-ultra-moon"}],"type":"normal","category":"status","power":null,"accuracy":null,"pp":20,"pastValues":[{"versionGroup":"black-white","type":null,"power":0,"accuracy":null,"pp":null}]},{"name":"last-resort","details":[{"level":0,"method":"tutor","versionGroup":"omega-ruby-alpha-sapphire"},{"level":0,"method":"tutor","versionGroup":"ultra-sun-ultra-moon"}],"type":"normal","category":"physical","power":140,"accuracy":100,"pp":5,"pastValues":[{"versionGroup":"black-white","type":null,"power":130,"accuracy":null,"pp":null}]},{"name":"poison-jab","details":[{"level":0,"method":"machine","versionGroup":"x-y"},{"level":0,"method":"machine","versionGroup":"omega-ruby-alpha-sapphire"},{"level":0,"method":"machine","versionGroup":"sun-moon"},{"level":0,"method":"machine","versionGroup":"ultra-sun-ultra-moon"},{"level":0,"method":"machine","versionGroup":"sword-shield"},{"level":0,"method":"machine","versionGroup":"scarlet-violet"}],"type":"poison","category":"physical","power":80,"accuracy":100,"pp":20,"pastValues":[]},{"name":"x-scissor","details":[{"level":0,"method":"machine","versionGroup":"x-y"},{"level":0,"method":"machine","versionGroup":"omega-ruby-alpha-sapphire"},{"level":0,"method":"machine","versionGroup":"sun-moon"},{"level":0,"method":"machine","versionGroup":"ultra-sun-ultra-moon"},{"level":0,"method":"machine","versionGroup":"sword-shield"},{"level":0,"method":"machine","versionGroup":"scarlet-violet"}],"type":"bug","category":"physical","power":80,"accuracy":100,"pp":15,"pastValues":[]},{"name":"drain-punch","details":[{"level":0,"method":"tutor","versionGroup":"omega-ruby-alpha-sapphire"},{"level":0,"method":"tutor","versionGroup":"ultra-sun-ultra-moon"},{"level":0,"method":"machine","versionGroup":"sword-shield"},{"level":0,"method":"machine","versionGroup":"scarlet-violet"}],"type":"fighting","category":"physical","power":75,"accuracy":100,"pp":10,"pastValues":[{"versionGroup":"black-white","type":null,"power":60,"accuracy":null,"pp":5}]},{"name":"focus-blast","details":[{"level":0,"method":"machine","versionGroup":"x-y"},{"level":0,"method":"machine","versionGroup":"omega-ruby-alpha-sapphire"},{"level":0,"method":"machine","versionGroup":"sun-moon"},{"level":0,"method":"machine","versionGroup":"ultra-sun-ultra-moon"},{"level":0,"method":"machine","versionGroup":"sword-shield"},{"level":0,"method":"machine","versionGroup":"scarlet-violet"}],"type":"fighting","category":"special","power":120,"accuracy":70,"pp":5,"pastValues":[]},{"name":"brave-bird","details":[{"level":0,"method":"machine","versionGroup":"sword-shield"},{"level":0,"method":"machine","versionGroup":"scarlet-violet"}],"type":"flying","category":"physical","power":120,"accuracy":100,"pp":15,"pastValues":[]},{"name":"giga-impact","details":[{"level":0,"method":"machine","versionGroup":"x-y"},{"level":0,"method":"machine","versionGroup":"omega-ruby-alpha-sapphire"},{"level":0,"method":"machine","versionGroup":"sun-moon"},{"level":0,"method":"machine","versionGroup":"ultra-sun-ultra-moon"},{"level":0,"method":"machine","versionGroup":"sword-shield"},{"level":0,"method":"machine","versionGroup":"scarlet-violet"}],"type":"normal","category":"physical","power":150,"accuracy":90,"pp":5,"pastValues":[]},{"name":"zen-headbutt","details":[{"level":0,"method":"tutor","versionGroup":"omega-ruby-alpha-sapphire"},{"level":0,"method":"tutor","versionGroup":"ultra-sun-ultra-moon"},{"level":0,"method":"machine","versionGroup":"sword-shield"},{"level":0,"method":"machine","versionGroup":"scarlet-violet"}],"type":"psychic","category":"physical","power":80,"accuracy":90,"pp":15,"pastValues":[]},{"name":"defog","details":[{"level":0,"method":"tutor","versionGroup":"ultra-sun-ultra-moon"},{"level":0,"method":"egg","versionGroup":"sword-shield"},{"level":0,"method":"egg","versionGroup":"scarlet-violet"}],"type":"flying","category":"status","power":null,"accuracy":null,"pp":15,"pastValues":[]},{"name":"iron-head","details":[{"level":0,"method":"tutor","versionGroup":"omega-ruby-alpha-sapphire"},{"level":0,"method":"tutor","versionGroup":"ultra-sun-ultra-moon"},{"level":0,"method":"machine","versionGroup":"sword-shield"},{"level":0,"method":"machine","versionGroup":"scarlet-violet"}],"type":"steel","category":"physical","power":80,"accuracy":100,"pp":15,"pastValues":[]},{"name":"stone-edge","details":[{"level":0,"method":"machine","versionGroup":"x-y"},{"level":0,"method":"machine","versionGroup":"omega-ruby-alpha-sapphire"},{"level":0,"method":"machine","versionGroup":"sun-moon"},{"level":0,"method":"machine","versionGroup":"ultra-sun-ultra-moon"},{"level":0,"method":"machine","versionGroup":"sword-shield"},{"level":0,"method":"machine","versionGroup":"scarlet-violet"}],"type":"rock","category":"physical","power":100,"accuracy":80,"pp":5,"pastValues":[]},{"name":"grass-knot","details":[{"level":0,"method":"machine","versionGroup":"x-y"},{"level":0,"method":"machine","versionGroup":"omega-ruby-alpha-sapphire"},{"level":0,"method":"machine","versionGroup":"sun-moon"},{"level":0,"method":"machine","versionGroup":"ultra-sun-ultra-moon"},{"level":0,"method":"machine","versionGroup":"sword-shield"},{"level":0,"method":"machine","versionGroup":"scarlet-violet"}],"type":"grass","category":"special","power":null,"accuracy":100,"pp":20,"pastValues":[]},{"name":"hone-claws","details":[{"level":1,"method":"level-up","versionGroup":"x-y"},{"level":0,"method":"machine","versionGroup":"x-y"},{"level":1,"method":"level-up","versionGroup":"omega-ruby-alpha-sapphire"},{"level":0,"method":"machine","versionGroup":"omega-ruby-alpha-sapphire"},{"level":1,"method":"level-up","versionGroup":"sun-moon"},{"level":1,"method":"level-up","versionGroup":"ultra-sun-ultra-moon"},{"level":1,"method":"level-up","versionGroup":"sword-shield"},{"level":1,"method":"level-up","versionGroup":"scarlet-violet"}],"type":"dark","category":"status","power":null,"accuracy":null,"pp":15,"pastValues":[]},{"name":"low-sweep","details":[{"level":0,"method":"machine","versionGroup":"x-y"},{"level":0,"method":"machine","versionGroup":"omega-ruby-alpha-sapphire"},{"level":0,"method":"machine","versionGroup":"sun-moon"},{"level":0,"method":"machine","versionGroup":"ultra-sun-ultra-moon"},{"level":0,"method":"machine","versionGroup":"sword-shield"},{"level":0,"method":"machine","versionGroup":"scarlet-violet"}],"type":"fighting","category":"physical","power":65,"accuracy":100,"pp":20,"pastValues":[{"versionGroup":"x-y","type":null,"power":60,"accuracy":null,"pp":null}]},{"name":"entrainment","details":[{"level":0,"method":"egg","versionGroup":"x-y"},{"level":0,"method":"egg","versionGroup":"omega-ruby-alpha-sapphire"},{"level":0,"method":"egg","versionGroup":"sun-moon"},{"level":0,"method":"egg","versionGroup":"ultra-sun-ultra-moon"},{"level":0,"method":"egg","versionGroup":"sword-shield"},{"level":0,"method":"egg","versionGroup":"scarlet-violet"}],"type":"normal","category":"status","power":null,"accuracy":100,"pp":15,"pastValues":[]},{"name":"round","details":[{"level":0,"method":"machine","versionGroup":"x-y"},{"level":0,"method":"machine","versionGroup":"omega-ruby-alpha-sapphire"},{"level":0,"method":"machine","versionGroup":"sun-moon"},{"level":0,"method":"machine","versionGroup":"ultra-sun-ultra-moon"},{"level":0,"method":"machine","versionGroup":"sword-shield"}],"type":"normal","category":"special","power":60,"accuracy":100,"pp":15,"pastValues":[]},{"name":"quick-guard","details":[{"level":0,"method":"egg","versionGroup":"x-y"},{"level":0,"method":"egg","versionGroup":"omega-ruby-alpha-sapphire"},{"level":0,"method":"egg","versionGroup":"sun-moon"},{"level":0,"method":"egg","versionGroup":"ultra-sun-ultra-moon"},{"level":0,"method":"egg","versionGroup":"sword-shield"},{"level":0,"method":"egg","versionGroup":"scarlet-violet"}],"type":"fighting","category":"status","power":null,"accuracy":null,"pp":15,"pastValues":[]},{"name":"ally-switch","details":[{"level":0,"method":"egg","versionGroup":"x-y"},{"level":0,"method":"egg","versionGroup":"omega-ruby-alpha-sapphire"},{"level":0,"method":"egg","versionGroup":"sun-moon"},{"level":0,"method":"egg","versionGroup":"ultra-sun-ultra-moon"},{"level":0,"method":"tutor","versionGroup":"ultra-sun-ultra-moon"},{"level":0,"method":"machine","versionGroup":"sword-shield"}],"type":"psychic","category":"status","power":null,"accuracy":null,"pp":15,"pastValues":[]},{"name":"sky-drop","details":[{"level":55,"method":"level-up","versionGroup":"x-y"},{"level":0,"method":"machine","versionGroup":"x-y"},{"level":55,"method":"level-up","versionGroup":"omega-ruby-alpha-sapphire"},{"level":0,"method":"machine","versionGroup":"omega-ruby-alpha-sapphire"},{"level":55,"method":"level-up","versionGroup":"sun-moon"},{"level":0,"method":"machine","versionGroup":"sun-moon"},{"level":55,"method":"level-up","versionGroup":"ultra-sun-ultra-moon"},{"level":0,"method":"machine","versionGroup":"ultra-sun-ultra-moon"}],"type":"flying","category":"physical","power":60,"accuracy":100,"pp":10,"pastValues":[]},{"name":"acrobatics","details":[{"level":0,"method":"machine","versionGroup":"x-y"},{"level":0,"method":"machine","versionGroup":"omega-ruby-alpha-sapphire"},{"level":0,"method":"machine","versionGroup":"sun-moon"},{"level":0,"method":"machine","versionGroup":"ultra-sun-ultra-moon"},{"level":0,"method":"machine","versionGroup":"sword-shield"},{"level":0,"method":"machine","versionGroup":"scarlet-violet"}],"type":"flying","category":"physical","power":55,"accuracy":100,"pp":15,"pastValues":[]},{"name":"retaliate","details":[{"level":0,"method":"machine","versionGroup":"x-y"},{"level":0,"method":"machine","versionGroup":"omega-ruby-alpha-sapphire"},{"level":0,"method":"machine","versionGroup":"sword-shield"}],"type":"normal","category":"physical","power":70,"accuracy":100,"pp":5,"pastValues":[]},{"name":"work-up","details":[{"level":0,"method":"machine","versionGroup":"sun-moon"},{"level":0,"method":"machine","versionGroup":"ultra-sun-ultra-moon"},{"level":0,"method":"machine","versionGroup":"sword-shield"}],"type":"normal","category":"status","power":null,"accuracy":null,"pp":30,"pastValues":[]},{"name":"dual-chop","details":[{"level":0,"method":"tutor","versionGroup":"omega-ruby-alpha-sapphire"},{"level":0,"method":"tutor","versionGroup":"ultra-sun-ultra-moon"}],"type":"dragon","category":"physical","power":40,"accuracy":90,"pp":15,"pastValues":[]},{"name":"flying-press","details":[{"level":28,"method":"level-up","versionGroup":"x-y"},{"level":28,"method":"level-up","versionGroup":"omega-ruby-alpha-sapphire"},{"level":28,"method":"level-up","versionGroup":"sun-moon"},{"level":28,"method":"level-up","versionGroup":"ultra-sun-ultra-moon"},{"level":44,"method":"level-up","versionGroup":"sword-shield"},{"level":44,"method":"level-up","versionGroup":"scarlet-violet"}],"type":"fighting","category":"physical","power":100,"accuracy":95,"pp":10,"pastValues":[{"versionGroup":"sun-moon","type":null,"power":80,"accuracy":null,"pp":null}]},{"name":"confide","details":[{"level":0,"method":"machine","versionGroup":"x-y"},{"level":0,"method":"machine","versionGroup":"omega-ruby-alpha-sapphire"},{"level":0,"method":"machine","versionGroup":"sun-moon"},{"level":0,"method":"machine","versionGroup":"ultra-sun-ultra-moon"}],"type":"normal","category":"status","power":null,"accuracy":null,"pp":20,"pastValues":[]},{"name":"power-up-punch","details":[{"level":0,"method":"machine","versionGroup":"x-y"},{"level":0,"method":"machine","versionGroup":"omega-ruby-alpha-sapphire"}],"type":"fighting","category":"physical","power":40,"accuracy":100,"pp":20,"pastValues":[]},{"name":"laser-focus","details":[{"level":0,"method":"tutor","versionGroup":"ultra-sun-ultra-moon"}],"type":"normal","category":"status","power":null,"accuracy":null,"pp":30,"pastValues":[]},{"name":"throat-chop","details":[{"level":0,"method":"tutor","versionGroup":"ultra-sun-ultra-moon"},{"level":0,"method":"machine","versionGroup":"sword-shield"},{"level":0,"method":"machine","versionGroup":"scarlet-violet"}],"type":"dark","category":"physical","power":80,"accuracy":100,"pp":15,"pastValues":[]},{"name":"lunge","details":[{"level":0,"method":"machine","versionGroup":"scarlet-violet"}],"type":"bug","category":"physical","power":80,"accuracy":100,"pp":15,"pastValues":[]},{"name":"body-press","details":[{"level":0,"method":"machine","versionGroup":"sword-shield"},{"level":0,"method":"machine","versionGroup":"scarlet-violet"}],"type":"fighting","category":"physical","power":80,"accuracy":100,"pp":10,"pastValues":[]},{"name":"coaching","details":[{"level":0,"method":"tutor","versionGroup":"sword-shield"},{"level":0,"method":"machine","versionGroup":"scarlet-violet"}],"type":"fighting","category":"status","power":null,"accuracy":null,"pp":10,"pastValues":[]},{"name":"dual-wingbeat","details":[{"level":0,"method":"tutor","versionGroup":"sword-shield"},{"level":0,"method":"machine","versionGroup":"scarlet-violet"}],"type":"flying","category":"physical","power":40,"accuracy":90,"pp":10,"pastValues":[]},{"name":"tera-blast","details":[{"level":0,"method":"machine","versionGroup":"scarlet-violet"}],"type":"normal","category":"special","power":80,"accuracy":100,"pp":10,"pastValues":[]},{"name":"trailblaze","details":[{"level":0,"method":"machine","versionGroup":"scarlet-violet"}],"type":"grass","category":"physical","power":50,"accuracy":100,"pp":20,"pastValues":[]},{"name":"upper-hand","details":[{"level":0,"method":"machine","versionGroup":"scarlet-violet"}],"type":"fighting","category":"physical","power":65,"accuracy":100,"pp":15,"pastValues":[]}],"evolutionRoot":{"name":"hawlucha","generation":6,"condition":null,"varieties":["hawlucha","hawlucha-mega"],"children":[]},"alternativeForms":[{"name":"hawlucha-mega"}]}