{"id":10203,"name":"kingler-gmax","image":"https://raw.githubusercontent.com/PokeAPI/sprites/master/sprites/pokemon/other/official-artwork/10203.png","shinyImage":"https://raw.githubusercontent.com/PokeAPI/sprites/master/sprites/pokemon/other/official-artwork/shiny/10203.png","types":["water"],"stats":[{"name":"hp","value":55},{"name":"attack","value":130},{"name":"defense","value":115},{"name":"special-attack","value":50},{"name":"special-defense","value":50},{"name":"speed","value":75}],"statTotal":475,"introducedGeneration":1,"abilities":[{"name":"hyper-cutter","hidden":false,"introducedIn":3,"description":"Prevents Attack from being lowered by other Pokémon.","effectChanges":[{"versionGroup":"emerald","description":"Has no overworld effect."},{"versionGroup":"diamond-pearl","description":"Doubles cut's grass-cutting radius on the overworld if any party Pokémon has this ability."}]},{"name":"shell-armor","hidden":false,"introducedIn":3,"description":"Protects against critical hits.","effectChanges":[]},{"name":"sheer-force","hidden":true,"introducedIn":5,"description":"Strengthens moves with extra effects to 1.3× their power, but prevents their extra effects.","effectChanges":[]}],"moves":[],"evolutionRoot":{"name":"krabby","generation":1,"condition":null,"varieties":["krabby"],"children":[{"name":"kingler","generation":1,"condition":"Lvl 28","varieties":["kingler","kingler-gmax"],"children":[]}]},"alternativeForms":[{"name":"kingler-gmax"}]}