{"name":"overcoat","generation":{"name":"generation-v","url":"https://pokeapi.co/api/v2/generation/5/"},"effect_entries":[{"effect":"Ce Pokémon ne subit pas de dégât de la météo.","language":{"name":"fr","url":"https://pokeapi.co/api/v2/language/5/"},"short_effect":"Protège contre les dégâts de la météo."},{"effect":"Pokémon mit dieser Fähigkeit erhalten keinen Schaden durch Wettereffekte.","language":{"name":"de","url":"https://pokeapi.co/api/v2/language/6/"},"short_effect":"Schützt vor Schäden durch weather."},{"effect":"This Pokémon does not take damage from weather.","language":{"name":"en","url":"https://pokeapi.co/api/v2/language/9/"},"short_effect":"Protects against damage from weather."}],"effect_changes":[]}