{"name":"pastel-veil","generation":{"name":"generation-viii","url":"https://pokeapi.co/api/v2/generation/8/"},"effect_entries":[{"effect":"Empêche le Pokémon et ses alliés d'être empoisonnés. Il soigne aussi les alliés du poison quand il entre sur le champ de bataille.","language":{"name":"fr","url":"https://pokeapi.co/api/v2/language/5/"},"short_effect":"Empêche le Pokémon et ses alliés d’être empoisonnés."},{"effect":"Prevents the Pokémon and its teammates from being poisoned. It also cures teammates of poisoning when it enters the battlefield.","language":{"name":"en","url":"https://pokeapi.co/api/v2/language/9/"},"short_effect":"Prevents the Pokémon and its allies from being poisoned."}],"effect_changes":[]}