{"name":"rain-dish","generation":{"name":"generation-iii","url":"https://pokeapi.co/api/v2/generation/3/"},"effect_entries":[{"effect":"Ce Pokémon soigne 1/16 de ses PV maximum après chaque tour sous pluie.","language":{"name":"fr","url":"https://pokeapi.co/api/v2/language/5/"},"short_effect":"Soigne 1/16 des PV max après chaque tour sous la pluie."},{"effect":"Pokémon mit dieser Fähigkeit heilen am Ende jeder Runde 1/16 ihrer maximalen hp wenn es regnet.","language":{"name":"de","url":"https://pokeapi.co/api/v2/language/6/"},"short_effect":"Heilt jede Runde 1/16 der maximalen hp wenn es regnet."},{"effect":"This Pokémon heals for 1/16 of its maximum HP after each turn during rain.","language":{"name":"en","url":"https://pokeapi.co/api/v2/language/9/"},"short_effect":"Heals for 1/16 max HP after each turn during rain."}],"effect_changes":[]}