{"name":"brine","power":65,"accuracy":100,"pp":10,"effect_chance":null,"damage_class":{"name":"special","url":"https://pokeapi.co/api/v2/move-damage-class/3/"},"type":{"name":"water","url":"https://pokeapi.co/api/v2/type/11/"},"effect_entries":[{"effect":"Inflige des dégâts réguliers.  Si la cible a moins de la moitié de ses PV max restants, cette capacité a une puissance double.","language":{"name":"fr","url":"https://pokeapi.co/api/v2/language/5/"},"short_effect":"A une puissance double contre les Pokémon qui ont moins de la moitié de leurs PV max restants."},{"effect":"Inflicts regular damage.  If the target has less than half its max HP remaining, this move has double power.","language":{"name":"en","url":"https://pokeapi.co/api/v2/language/9/"},"short_effect":"Has double power against Pokémon that have less than half their max HP remaining."}],"past_values":[]}