{"name":"confusion","power":50,"accuracy":100,"pp":25,"effect_chance":10,"damage_class":{"name":"special","url":"https://pokeapi.co/api/v2/move-damage-class/3/"},"type":{"name":"psychic","url":"https://pokeapi.co/api/v2/type/14/"},"effect_entries":[{"effect":"Inflige des dégats réguliers.  A une $probabilité_d'effet% de chances de rendre la cible confuse.","language":{"name":"fr","url":"https://pokeapi.co/api/v2/language/5/"},"short_effect":"A une $probabilité_d'effet% de chances de rendre la cible confuse."},{"effect":"Inflicts regular damage.  Has a $effect_chance% chance to confuse the target.","language":{"name":"en","url":"https://pokeapi.co/api/v2/language/9/"},"short_effect":"Has a $effect_chance% chance to confuse the target."}],"past_values":[]}