{"name":"light-of-ruin","power":140,"accuracy":90,"pp":5,"effect_chance":null,"damage_class":{"name":"special","url":"https://pokeapi.co/api/v2/move-damage-class/3/"},"type":{"name":"fairy","url":"https://pokeapi.co/api/v2/type/18/"},"effect_entries":[{"effect":"Inflige des dégâts réguliers.  Le lanceur subit 1/2 des dégâts qu'il inflige en contrecoup.","language":{"name":"fr","url":"https://pokeapi.co/api/v2/language/5/"},"short_effect":"Le lanceur reçoit 1/2 des dégâts infligés en contrecoup."},{"effect":"Inflicts regular damage.  User takes 1/2 the damage it inflicts in recoil.","language":{"name":"en","url":"https://pokeapi.co/api/v2/language/9/"},"short_effect":"User receives 1/2 the damage inflicted in recoil."}],"past_values":[]}