{"name":"rage-powder","power":null,"accuracy":null,"pp":20,"effect_chance":null,"damage_class":{"name":"status","url":"https://pokeapi.co/api/v2/move-damage-class/1/"},"type":{"name":"bug","url":"https://pokeapi.co/api/v2/type/7/"},"effect_entries":[{"effect":"Jusqu'à la fin de ce tour, n'importe quelle capacité qu'un Pokémon adverse qui cible seulement un allié du lanceur ciblera le lanceur à la place.  Si les deux Pokémon du même côté du terrain utilisent cette capacité le même tour, le Pokémon qui l'utilise en dernier deviendra la cible.\n\nCet effet prend la priorité sur lightning rod et storm drain.\n\nSi l'allié du lanceur se retire, les Pokémon adverses peuvent toujours le frapper avec pursuit.\n\nCette capacité ne peut pas être sélectionnée par assist ou metronome.","language":{"name":"fr","url":"https://pokeapi.co/api/v2/language/5/"},"short_effect":"Redirige les effets de l'attaque à cible unique de la cible sur le lanceur pendant ce tour."},{"effect":"Until the end of this turn, any moves that opposing Pokémon target solely at the user’s ally will instead target the user.  If both Pokémon on the same side of the field use this move on the same turn, the Pokémon that uses it last will become the target.\n\nThis effect takes priority over lightning rod and storm drain.\n\nIf the user’s ally switches out, opposing Pokémon may still hit it with pursuit.\n\nThis move cannot be selected by assist or metronome.","language":{"name":"en","url":"https://pokeapi.co/api/v2/language/9/"},"short_effect":"Redirects the target’s single-target effects to the user for this turn."}],"past_values":[{"accuracy":null,"effect_chance":null,"effect_entries":[{"effect":"Inflige des dégats réguliers.  A une $probabilité_d'effet% de chances d'empoisonner la cible.","language":{"name":"fr","url":"https://pokeapi.co/api/v2/language/5/"},"short_effect":"A une $probabilité_d'effet% de chances d'empoisonner la cible."},{"effect":"Inflicts regular damage.  Has a $effect_chance% chance to poison the target.","language":{"name":"en","url":"https://pokeapi.co/api/v2/language/9/"},"short_effect":"Has a $effect_chance% chance to poison the target."}],"power":null,"pp":null,"type":null,"version_group":{"name":"x-y","url":"https://pokeapi.co/api/v2/version-group/15/"}}]}